{"order":{"user":"Han-Chi","userID":"220675402971086850","channelID":"264461209649020930","event":{"t":"MESSAGE_CREATE","s":20,"op":0,"d":{"type":0,"tts":false,"timestamp":"2016-12-31T01:06:38.354000+00:00","pinned":false,"nonce":"264559911118045184","mentions":[],"mention_roles":[],"mention_everyone":false,"id":"264559912200175617","embeds":[],"edited_timestamp":null,"content":"/askwq Last furry thing you touched?","channel_id":"264461209649020930","author":{"username":"Han-Chi","id":"220675402971086850","discriminator":"4141","avatar":"897026fda4084d2e9cc6c88d7d4acf9c"},"attachments":[]}},"cmd":"askwq","args":["Last","furry","thing","you","touched?"]},"question":"Last furry thing you touched? ","answers":[],"id":"220675402971086850-1483146398544"}